test_first_jl_extension/__init__.py
test_first_jl_extension/_version.py
test_first_jl_extension/cfg.py
test_first_jl_extension/plugin.py
test_first_jl_extension-0.1.0.data/data/share/jupyter/labextensions/test-first-jl-extension/build_log.json
test_first_jl_extension-0.1.0.data/data/share/jupyter/labextensions/test-first-jl-extension/package.json
test_first_jl_extension-0.1.0.data/data/share/jupyter/labextensions/test-first-jl-extension/schemas/test-first-jl-extension/package.json.orig
test_first_jl_extension-0.1.0.data/data/share/jupyter/labextensions/test-first-jl-extension/schemas/test-first-jl-extension/plugin.json
test_first_jl_extension-0.1.0.data/data/share/jupyter/labextensions/test-first-jl-extension/static/lib_index_js-webpack_sharing_consume_default_jupyterlab_coreutils.800ad50d0caa5da2dce6.js
test_first_jl_extension-0.1.0.data/data/share/jupyter/labextensions/test-first-jl-extension/static/lib_index_js-webpack_sharing_consume_default_jupyterlab_coreutils.800ad50d0caa5da2dce6.js.map
test_first_jl_extension-0.1.0.data/data/share/jupyter/labextensions/test-first-jl-extension/static/remoteEntry.a4acbc13928c69b4e85d.js
test_first_jl_extension-0.1.0.data/data/share/jupyter/labextensions/test-first-jl-extension/static/remoteEntry.a4acbc13928c69b4e85d.js.map
test_first_jl_extension-0.1.0.data/data/share/jupyter/labextensions/test-first-jl-extension/static/style.js
test_first_jl_extension-0.1.0.data/data/share/jupyter/labextensions/test-first-jl-extension/static/style_index_js.055496728e6ae44ea3fc.js
test_first_jl_extension-0.1.0.data/data/share/jupyter/labextensions/test-first-jl-extension/static/style_index_js.055496728e6ae44ea3fc.js.map
test_first_jl_extension-0.1.0.data/data/share/jupyter/labextensions/test-first-jl-extension/static/vendors-node_modules_css-loader_dist_runtime_api_js-node_modules_css-loader_dist_runtime_cssW-72eba1.40655a9b53bc6ab8549a.js
test_first_jl_extension-0.1.0.dist-info/METADATA
test_first_jl_extension-0.1.0.dist-info/WHEEL
test_first_jl_extension-0.1.0.dist-info/entry_points.txt
test_first_jl_extension-0.1.0.dist-info/licenses/LICENSE
test_first_jl_extension-0.1.0.dist-info/RECORD
